[{"starred_at":"2020-05-28T04:23:24Z","user":{"login":"jlwg","id":8544950,"node_id":"MDQ6VXNlcjg1NDQ5NTA=","avatar_url":"https://avatars.githubusercontent.com/u/8544950?v=4","gravatar_id":"","url":"https://api.github.com/users/jlwg","html_url":"https://github.com/jlwg","followers_url":"https://api.github.com/users/jlwg/followers","following_url":"https://api.github.com/users/jlwg/following{/other_user}","gists_url":"https://api.github.com/users/jlwg/gists{/gist_id}","starred_url":"https://api.github.com/users/jlwg/starred{/owner}{/repo}","subscriptions_url":"https://api.github.com/users/jlwg/subscriptions","organizations_url":"https://api.github.com/users/jlwg/orgs","repos_url":"https://api.github.com/users/jlwg/repos","events_url":"https://api.github.com/users/jlwg/events{/privacy}","received_events_url":"https://api.github.com/users/jlwg/received_events","type":"User","site_admin":false}},{"starred_at":"2020-05-28T19:08:01Z","user":{"login":"swanom","id":32580863,"node_id":"MDQ6VXNlcjMyNTgwODYz","avatar_url":"https://avatars.githubusercontent.com/u/32580863?v=4","gravatar_id":"","url":"https://api.github.com/users/swanom","html_url":"https://github.com/swanom","followers_url":"https://api.github.com/users/swanom/followers","following_url":"https://api.github.com/users/swanom/following{/other_user}","gists_url":"https://api.github.com/users/swanom/gists{/gist_id}","starred_url":"https://api.github.com/users/swanom/starred{/owner}{/repo}","subscriptions_url":"https://api.github.com/users/swanom/subscriptions","organizations_url":"https://api.github.com/users/swanom/orgs","repos_url":"https://api.github.com/users/swanom/repos","events_url":"https://api.github.com/users/swanom/events{/privacy}","received_events_url":"https://api.github.com/users/swanom/received_events","type":"User","site_admin":false}},{"starred_at":"2020-05-29T00:45:30Z","user":{"login":"HowardWhile","id":18715360,"node_id":"MDQ6VXNlcjE4NzE1MzYw","avatar_url":"https://avatars.githubusercontent.com/u/18715360?v=4","gravatar_id":"","url":"https://api.github.com/users/HowardWhile","html_url":"https://github.com/HowardWhile","followers_url":"https://api.github.com/users/HowardWhile/followers","following_url":"https://api.github.com/users/HowardWhile/following{/other_user}","gists_url":"https://api.github.com/users/HowardWhile/gists{/gist_id}","starred_url":"https://api.github.com/users/HowardWhile/starred{/owner}{/repo}","subscriptions_url":"https://api.github.com/users/HowardWhile/subscriptions","organizations_url":"https://api.github.com/users/HowardWhile/orgs","repos_url":"https://api.github.com/users/HowardWhile/repos","events_url":"https://api.github.com/users/HowardWhile/events{/privacy}","received_events_url":"https://api.github.com/users/HowardWhile/received_events","type":"User","site_admin":false}},{"starred_at":"2020-05-29T18:47:29Z","user":{"login":"forexskriabinss","id":48759484,"node_id":"MDQ6VXNlcjQ4NzU5NDg0","avatar_url":"https://avatars.githubusercontent.com/u/48759484?v=4","gravatar_id":"","url":"https://api.github.com/users/forexskriabinss","html_url":"https://github.com/forexskriabinss","followers_url":"https://api.github.com/users/forexskriabinss/followers","following_url":"https://api.github.com/users/forexskriabinss/following{/other_user}","gists_url":"https://api.github.com/users/forexskriabinss/gists{/gist_id}","starred_url":"https://api.github.com/users/forexskriabinss/starred{/owner}{/repo}","subscriptions_url":"https://api.github.com/users/forexskriabinss/subscriptions","organizations_url":"https://api.github.com/users/forexskriabinss/orgs","repos_url":"https://api.github.com/users/forexskriabinss/repos","events_url":"https://api.github.com/users/forexskriabinss/events{/privacy}","received_events_url":"https://api.github.com/users/forexskriabinss/received_events","type":"User","site_admin":false}},{"starred_at":"2020-05-30T06:24:29Z","user":{"login":"aixia8383","id":50036321,"node_id":"MDQ6VXNlcjUwMDM2MzIx","avatar_url":"https://avatars.githubusercontent.com/u/50036321?v=4","gravatar_id":"","url":"https://api.github.com/users/aixia8383","html_url":"https://github.com/aixia8383","followers_url":"https://api.github.com/users/aixia8383/followers","following_url":"https://api.github.com/users/aixia8383/following{/other_user}","gists_url":"https://api.github.com/users/aixia8383/gists{/gist_id}","starred_url":"https://api.github.com/users/aixia8383/starred{/owner}{/repo}","subscriptions_url":"https://api.github.com/users/aixia8383/subscriptions","organizations_url":"https://api.github.com/users/aixia8383/orgs","repos_url":"https://api.github.com/users/aixia8383/repos","events_url":"https://api.github.com/users/aixia8383/events{/privacy}","received_events_url":"https://api.github.com/users/aixia8383/received_events","type":"User","site_admin":false}},{"starred_at":"2020-05-31T12:34:43Z","user":{"login":"dshe","id":750168,"node_id":"MDQ6VXNlcjc1MDE2OA==","avatar_url":"https://avatars.githubusercontent.com/u/750168?v=4","gravatar_id":"","url":"https://api.github.com/users/dshe","html_url":"https://github.com/dshe","followers_url":"https://api.github.com/users/dshe/followers","following_url":"https://api.github.com/users/dshe/following{/other_user}","gists_url":"https://api.github.com/users/dshe/gists{/gist_id}","starred_url":"https://api.github.com/users/dshe/starred{/owner}{/repo}","subscriptions_url":"https://api.github.com/users/dshe/subscriptions","organizations_url":"https://api.github.com/users/dshe/orgs","repos_url":"https://api.github.com/users/dshe/repos","events_url":"https://api.github.com/users/dshe/events{/privacy}","received_events_url":"https://api.github.com/users/dshe/received_events","type":"User","site_admin":false}},{"starred_at":"2020-06-01T08:02:34Z","user":{"login":"Theleme","id":35056831,"node_id":"MDQ6VXNlcjM1MDU2ODMx","avatar_url":"https://avatars.githubusercontent.com/u/35056831?v=4","gravatar_id":"","url":"https://api.github.com/users/Theleme","html_url":"https://github.com/Theleme","followers_url":"https://api.github.com/users/Theleme/followers","following_url":"https://api.github.com/users/Theleme/following{/other_user}","gists_url":"https://api.github.com/users/Theleme/gists{/gist_id}","starred_url":"https://api.github.com/users/Theleme/starred{/owner}{/repo}","subscriptions_url":"https://api.github.com/users/Theleme/subscriptions","organizations_url":"https://api.github.com/users/Theleme/orgs","repos_url":"https://api.github.com/users/Theleme/repos","events_url":"https://api.github.com/users/Theleme/events{/privacy}","received_events_url":"https://api.github.com/users/Theleme/received_events","type":"User","site_admin":false}},{"starred_at":"2020-06-03T18:23:09Z","user":{"login":"bwagner1001","id":31707627,"node_id":"MDQ6VXNlcjMxNzA3NjI3","avatar_url":"https://avatars.githubusercontent.com/u/31707627?v=4","gravatar_id":"","url":"https://api.github.com/users/bwagner1001","html_url":"https://github.com/bwagner1001","followers_url":"https://api.github.com/users/bwagner1001/followers","following_url":"https://api.github.com/users/bwagner1001/following{/other_user}","gists_url":"https://api.github.com/users/bwagner1001/gists{/gist_id}","starred_url":"https://api.github.com/users/bwagner1001/starred{/owner}{/repo}","subscriptions_url":"https://api.github.com/users/bwagner1001/subscriptions","organizations_url":"https://api.github.com/users/bwagner1001/orgs","repos_url":"https://api.github.com/users/bwagner1001/repos","events_url":"https://api.github.com/users/bwagner1001/events{/privacy}","received_events_url":"https://api.github.com/users/bwagner1001/received_events","type":"User","site_admin":false}},{"starred_at":"2020-06-03T23:36:05Z","user":{"login":"moisestohias","id":48728934,"node_id":"MDQ6VXNlcjQ4NzI4OTM0","avatar_url":"https://avatars.githubusercontent.com/u/48728934?v=4","gravatar_id":"","url":"https://api.github.com/users/moisestohias","html_url":"https://github.com/moisestohias","followers_url":"https://api.github.com/users/moisestohias/followers","following_url":"https://api.github.com/users/moisestohias/following{/other_user}","gists_url":"https://api.github.com/users/moisestohias/gists{/gist_id}","starred_url":"https://api.github.com/users/moisestohias/starred{/owner}{/repo}","subscriptions_url":"https://api.github.com/users/moisestohias/subscriptions","organizations_url":"https://api.github.com/users/moisestohias/orgs","repos_url":"https://api.github.com/users/moisestohias/repos","events_url":"https://api.github.com/users/moisestohias/events{/privacy}","received_events_url":"https://api.github.com/users/moisestohias/received_events","type":"User","site_admin":false}},{"starred_at":"2020-06-04T05:52:12Z","user":{"login":"yijidao","id":24776101,"node_id":"MDQ6VXNlcjI0Nzc2MTAx","avatar_url":"https://avatars.githubusercontent.com/u/24776101?v=4","gravatar_id":"","url":"https://api.github.com/users/yijidao","html_url":"https://github.com/yijidao","followers_url":"https://api.github.com/users/yijidao/followers","following_url":"https://api.github.com/users/yijidao/following{/other_user}","gists_url":"https://api.github.com/users/yijidao/gists{/gist_id}","starred_url":"https://api.github.com/users/yijidao/starred{/owner}{/repo}","subscriptions_url":"https://api.github.com/users/yijidao/subscriptions","organizations_url":"https://api.github.com/users/yijidao/orgs","repos_url":"https://api.github.com/users/yijidao/repos","events_url":"https://api.github.com/users/yijidao/events{/privacy}","received_events_url":"https://api.github.com/users/yijidao/received_events","type":"User","site_admin":false}},{"starred_at":"2020-06-05T04:10:37Z","user":{"login":"rexcardan","id":2116960,"node_id":"MDQ6VXNlcjIxMTY5NjA=","avatar_url":"https://avatars.githubusercontent.com/u/2116960?v=4","gravatar_id":"","url":"https://api.github.com/users/rexcardan","html_url":"https://github.com/rexcardan","followers_url":"https://api.github.com/users/rexcardan/followers","following_url":"https://api.github.com/users/rexcardan/following{/other_user}","gists_url":"https://api.github.com/users/rexcardan/gists{/gist_id}","starred_url":"https://api.github.com/users/rexcardan/starred{/owner}{/repo}","subscriptions_url":"https://api.github.com/users/rexcardan/subscriptions","organizations_url":"https://api.github.com/users/rexcardan/orgs","repos_url":"https://api.github.com/users/rexcardan/repos","events_url":"https://api.github.com/users/rexcardan/events{/privacy}","received_events_url":"https://api.github.com/users/rexcardan/received_events","type":"User","site_admin":false}},{"starred_at":"2020-06-07T03:34:07Z","user":{"login":"gobikulandaisamy","id":24189431,"node_id":"MDQ6VXNlcjI0MTg5NDMx","avatar_url":"https://avatars.githubusercontent.com/u/24189431?v=4","gravatar_id":"","url":"https://api.github.com/users/gobikulandaisamy","html_url":"https://github.com/gobikulandaisamy","followers_url":"https://api.github.com/users/gobikulandaisamy/followers","following_url":"https://api.github.com/users/gobikulandaisamy/following{/other_user}","gists_url":"https://api.github.com/users/gobikulandaisamy/gists{/gist_id}","starred_url":"https://api.github.com/users/gobikulandaisamy/starred{/owner}{/repo}","subscriptions_url":"https://api.github.com/users/gobikulandaisamy/subscriptions","organizations_url":"https://api.github.com/users/gobikulandaisamy/orgs","repos_url":"https://api.github.com/users/gobikulandaisamy/repos","events_url":"https://api.github.com/users/gobikulandaisamy/events{/privacy}","received_events_url":"https://api.github.com/users/gobikulandaisamy/received_events","type":"User","site_admin":false}},{"starred_at":"2020-06-08T03:34:12Z","user":{"login":"minikie","id":12060492,"node_id":"MDQ6VXNlcjEyMDYwNDky","avatar_url":"https://avatars.githubusercontent.com/u/12060492?v=4","gravatar_id":"","url":"https://api.github.com/users/minikie","html_url":"https://github.com/minikie","followers_url":"https://api.github.com/users/minikie/followers","following_url":"https://api.github.com/users/minikie/following{/other_user}","gists_url":"https://api.github.com/users/minikie/gists{/gist_id}","starred_url":"https://api.github.com/users/minikie/starred{/owner}{/repo}","subscriptions_url":"https://api.github.com/users/minikie/subscriptions","organizations_url":"https://api.github.com/users/minikie/orgs","repos_url":"https://api.github.com/users/minikie/repos","events_url":"https://api.github.com/users/minikie/events{/privacy}","received_events_url":"https://api.github.com/users/minikie/received_events","type":"User","site_admin":false}},{"starred_at":"2020-06-09T00:58:18Z","user":{"login":"arpnet","id":8731486,"node_id":"MDQ6VXNlcjg3MzE0ODY=","avatar_url":"https://avatars.githubusercontent.com/u/8731486?v=4","gravatar_id":"","url":"https://api.github.com/users/arpnet","html_url":"https://github.com/arpnet","followers_url":"https://api.github.com/users/arpnet/followers","following_url":"https://api.github.com/users/arpnet/following{/other_user}","gists_url":"https://api.github.com/users/arpnet/gists{/gist_id}","starred_url":"https://api.github.com/users/arpnet/starred{/owner}{/repo}","subscriptions_url":"https://api.github.com/users/arpnet/subscriptions","organizations_url":"https://api.github.com/users/arpnet/orgs","repos_url":"https://api.github.com/users/arpnet/repos","events_url":"https://api.github.com/users/arpnet/events{/privacy}","received_events_url":"https://api.github.com/users/arpnet/received_events","type":"User","site_admin":false}},{"starred_at":"2020-06-09T02:37:25Z","user":{"login":"luyongqiang","id":3412156,"node_id":"MDQ6VXNlcjM0MTIxNTY=","avatar_url":"https://avatars.githubusercontent.com/u/3412156?v=4","gravatar_id":"","url":"https://api.github.com/users/luyongqiang","html_url":"https://github.com/luyongqiang","followers_url":"https://api.github.com/users/luyongqiang/followers","following_url":"https://api.github.com/users/luyongqiang/following{/other_user}","gists_url":"https://api.github.com/users/luyongqiang/gists{/gist_id}","starred_url":"https://api.github.com/users/luyongqiang/starred{/owner}{/repo}","subscriptions_url":"https://api.github.com/users/luyongqiang/subscriptions","organizations_url":"https://api.github.com/users/luyongqiang/orgs","repos_url":"https://api.github.com/users/luyongqiang/repos","events_url":"https://api.github.com/users/luyongqiang/events{/privacy}","received_events_url":"https://api.github.com/users/luyongqiang/received_events","type":"User","site_admin":false}},{"starred_at":"2020-06-10T15:20:16Z","user":{"login":"JettFlat","id":45435662,"node_id":"MDQ6VXNlcjQ1NDM1NjYy","avatar_url":"https://avatars.githubusercontent.com/u/45435662?v=4","gravatar_id":"","url":"https://api.github.com/users/JettFlat","html_url":"https://github.com/JettFlat","followers_url":"https://api.github.com/users/JettFlat/followers","following_url":"https://api.github.com/users/JettFlat/following{/other_user}","gists_url":"https://api.github.com/users/JettFlat/gists{/gist_id}","starred_url":"https://api.github.com/users/JettFlat/starred{/owner}{/repo}","subscriptions_url":"https://api.github.com/users/JettFlat/subscriptions","organizations_url":"https://api.github.com/users/JettFlat/orgs","repos_url":"https://api.github.com/users/JettFlat/repos","events_url":"https://api.github.com/users/JettFlat/events{/privacy}","received_events_url":"https://api.github.com/users/JettFlat/received_events","type":"User","site_admin":false}},{"starred_at":"2020-06-10T16:14:12Z","user":{"login":"Orace","id":9695349,"node_id":"MDQ6VXNlcjk2OTUzNDk=","avatar_url":"https://avatars.githubusercontent.com/u/9695349?v=4","gravatar_id":"","url":"https://api.github.com/users/Orace","html_url":"https://github.com/Orace","followers_url":"https://api.github.com/users/Orace/followers","following_url":"https://api.github.com/users/Orace/following{/other_user}","gists_url":"https://api.github.com/users/Orace/gists{/gist_id}","starred_url":"https://api.github.com/users/Orace/starred{/owner}{/repo}","subscriptions_url":"https://api.github.com/users/Orace/subscriptions","organizations_url":"https://api.github.com/users/Orace/orgs","repos_url":"https://api.github.com/users/Orace/repos","events_url":"https://api.github.com/users/Orace/events{/privacy}","received_events_url":"https://api.github.com/users/Orace/received_events","type":"User","site_admin":false}},{"starred_at":"2020-06-11T02:38:14Z","user":{"login":"kreimnitz","id":66393516,"node_id":"MDQ6VXNlcjY2MzkzNTE2","avatar_url":"https://avatars.githubusercontent.com/u/66393516?v=4","gravatar_id":"","url":"https://api.github.com/users/kreimnitz","html_url":"https://github.com/kreimnitz","followers_url":"https://api.github.com/users/kreimnitz/followers","following_url":"https://api.github.com/users/kreimnitz/following{/other_user}","gists_url":"https://api.github.com/users/kreimnitz/gists{/gist_id}","starred_url":"https://api.github.com/users/kreimnitz/starred{/owner}{/repo}","subscriptions_url":"https://api.github.com/users/kreimnitz/subscriptions","organizations_url":"https://api.github.com/users/kreimnitz/orgs","repos_url":"https://api.github.com/users/kreimnitz/repos","events_url":"https://api.github.com/users/kreimnitz/events{/privacy}","received_events_url":"https://api.github.com/users/kreimnitz/received_events","type":"User","site_admin":false}},{"starred_at":"2020-06-11T15:01:14Z","user":{"login":"robokamran","id":8957516,"node_id":"MDQ6VXNlcjg5NTc1MTY=","avatar_url":"https://avatars.githubusercontent.com/u/8957516?v=4","gravatar_id":"","url":"https://api.github.com/users/robokamran","html_url":"https://github.com/robokamran","followers_url":"https://api.github.com/users/robokamran/followers","following_url":"https://api.github.com/users/robokamran/following{/other_user}","gists_url":"https://api.github.com/users/robokamran/gists{/gist_id}","starred_url":"https://api.github.com/users/robokamran/starred{/owner}{/repo}","subscriptions_url":"https://api.github.com/users/robokamran/subscriptions","organizations_url":"https://api.github.com/users/robokamran/orgs","repos_url":"https://api.github.com/users/robokamran/repos","events_url":"https://api.github.com/users/robokamran/events{/privacy}","received_events_url":"https://api.github.com/users/robokamran/received_events","type":"User","site_admin":false}},{"starred_at":"2020-06-12T15:09:51Z","user":{"login":"debonairWei","id":28428381,"node_id":"MDQ6VXNlcjI4NDI4Mzgx","avatar_url":"https://avatars.githubusercontent.com/u/28428381?v=4","gravatar_id":"","url":"https://api.github.com/users/debonairWei","html_url":"https://github.com/debonairWei","followers_url":"https://api.github.com/users/debonairWei/followers","following_url":"https://api.github.com/users/debonairWei/following{/other_user}","gists_url":"https://api.github.com/users/debonairWei/gists{/gist_id}","starred_url":"https://api.github.com/users/debonairWei/starred{/owner}{/repo}","subscriptions_url":"https://api.github.com/users/debonairWei/subscriptions","organizations_url":"https://api.github.com/users/debonairWei/orgs","repos_url":"https://api.github.com/users/debonairWei/repos","events_url":"https://api.github.com/users/debonairWei/events{/privacy}","received_events_url":"https://api.github.com/users/debonairWei/received_events","type":"User","site_admin":false}},{"starred_at":"2020-06-15T12:07:10Z","user":{"login":"JackywangBin","id":27112824,"node_id":"MDQ6VXNlcjI3MTEyODI0","avatar_url":"https://avatars.githubusercontent.com/u/27112824?v=4","gravatar_id":"","url":"https://api.github.com/users/JackywangBin","html_url":"https://github.com/JackywangBin","followers_url":"https://api.github.com/users/JackywangBin/followers","following_url":"https://api.github.com/users/JackywangBin/following{/other_user}","gists_url":"https://api.github.com/users/JackywangBin/gists{/gist_id}","starred_url":"https://api.github.com/users/JackywangBin/starred{/owner}{/repo}","subscriptions_url":"https://api.github.com/users/JackywangBin/subscriptions","organizations_url":"https://api.github.com/users/JackywangBin/orgs","repos_url":"https://api.github.com/users/JackywangBin/repos","events_url":"https://api.github.com/users/JackywangBin/events{/privacy}","received_events_url":"https://api.github.com/users/JackywangBin/received_events","type":"User","site_admin":false}},{"starred_at":"2020-06-17T02:06:15Z","user":{"login":"zyhong","id":5116559,"node_id":"MDQ6VXNlcjUxMTY1NTk=","avatar_url":"https://avatars.githubusercontent.com/u/5116559?v=4","gravatar_id":"","url":"https://api.github.com/users/zyhong","html_url":"https://github.com/zyhong","followers_url":"https://api.github.com/users/zyhong/followers","following_url":"https://api.github.com/users/zyhong/following{/other_user}","gists_url":"https://api.github.com/users/zyhong/gists{/gist_id}","starred_url":"https://api.github.com/users/zyhong/starred{/owner}{/repo}","subscriptions_url":"https://api.github.com/users/zyhong/subscriptions","organizations_url":"https://api.github.com/users/zyhong/orgs","repos_url":"https://api.github.com/users/zyhong/repos","events_url":"https://api.github.com/users/zyhong/events{/privacy}","received_events_url":"https://api.github.com/users/zyhong/received_events","type":"User","site_admin":false}},{"starred_at":"2020-06-17T07:55:30Z","user":{"login":"kumamiko","id":18533608,"node_id":"MDQ6VXNlcjE4NTMzNjA4","avatar_url":"https://avatars.githubusercontent.com/u/18533608?v=4","gravatar_id":"","url":"https://api.github.com/users/kumamiko","html_url":"https://github.com/kumamiko","followers_url":"https://api.github.com/users/kumamiko/followers","following_url":"https://api.github.com/users/kumamiko/following{/other_user}","gists_url":"https://api.github.com/users/kumamiko/gists{/gist_id}","starred_url":"https://api.github.com/users/kumamiko/starred{/owner}{/repo}","subscriptions_url":"https://api.github.com/users/kumamiko/subscriptions","organizations_url":"https://api.github.com/users/kumamiko/orgs","repos_url":"https://api.github.com/users/kumamiko/repos","events_url":"https://api.github.com/users/kumamiko/events{/privacy}","received_events_url":"https://api.github.com/users/kumamiko/received_events","type":"User","site_admin":false}},{"starred_at":"2020-06-18T16:43:41Z","user":{"login":"kapil-iitk","id":18379648,"node_id":"MDQ6VXNlcjE4Mzc5NjQ4","avatar_url":"https://avatars.githubusercontent.com/u/18379648?v=4","gravatar_id":"","url":"https://api.github.com/users/kapil-iitk","html_url":"https://github.com/kapil-iitk","followers_url":"https://api.github.com/users/kapil-iitk/followers","following_url":"https://api.github.com/users/kapil-iitk/following{/other_user}","gists_url":"https://api.github.com/users/kapil-iitk/gists{/gist_id}","starred_url":"https://api.github.com/users/kapil-iitk/starred{/owner}{/repo}","subscriptions_url":"https://api.github.com/users/kapil-iitk/subscriptions","organizations_url":"https://api.github.com/users/kapil-iitk/orgs","repos_url":"https://api.github.com/users/kapil-iitk/repos","events_url":"https://api.github.com/users/kapil-iitk/events{/privacy}","received_events_url":"https://api.github.com/users/kapil-iitk/received_events","type":"User","site_admin":false}},{"starred_at":"2020-06-19T06:35:55Z","user":{"login":"king657862114","id":33048981,"node_id":"MDQ6VXNlcjMzMDQ4OTgx","avatar_url":"https://avatars.githubusercontent.com/u/33048981?v=4","gravatar_id":"","url":"https://api.github.com/users/king657862114","html_url":"https://github.com/king657862114","followers_url":"https://api.github.com/users/king657862114/followers","following_url":"https://api.github.com/users/king657862114/following{/other_user}","gists_url":"https://api.github.com/users/king657862114/gists{/gist_id}","starred_url":"https://api.github.com/users/king657862114/starred{/owner}{/repo}","subscriptions_url":"https://api.github.com/users/king657862114/subscriptions","organizations_url":"https://api.github.com/users/king657862114/orgs","repos_url":"https://api.github.com/users/king657862114/repos","events_url":"https://api.github.com/users/king657862114/events{/privacy}","received_events_url":"https://api.github.com/users/king657862114/received_events","type":"User","site_admin":false}},{"starred_at":"2020-06-21T07:00:32Z","user":{"login":"ZTaiIT1025","id":38967376,"node_id":"MDQ6VXNlcjM4OTY3Mzc2","avatar_url":"https://avatars.githubusercontent.com/u/38967376?v=4","gravatar_id":"","url":"https://api.github.com/users/ZTaiIT1025","html_url":"https://github.com/ZTaiIT1025","followers_url":"https://api.github.com/users/ZTaiIT1025/followers","following_url":"https://api.github.com/users/ZTaiIT1025/following{/other_user}","gists_url":"https://api.github.com/users/ZTaiIT1025/gists{/gist_id}","starred_url":"https://api.github.com/users/ZTaiIT1025/starred{/owner}{/repo}","subscriptions_url":"https://api.github.com/users/ZTaiIT1025/subscriptions","organizations_url":"https://api.github.com/users/ZTaiIT1025/orgs","repos_url":"https://api.github.com/users/ZTaiIT1025/repos","events_url":"https://api.github.com/users/ZTaiIT1025/events{/privacy}","received_events_url":"https://api.github.com/users/ZTaiIT1025/received_events","type":"User","site_admin":false}},{"starred_at":"2020-06-21T07:44:03Z","user":{"login":"drkthng","id":3247479,"node_id":"MDQ6VXNlcjMyNDc0Nzk=","avatar_url":"https://avatars.githubusercontent.com/u/3247479?v=4","gravatar_id":"","url":"https://api.github.com/users/drkthng","html_url":"https://github.com/drkthng","followers_url":"https://api.github.com/users/drkthng/followers","following_url":"https://api.github.com/users/drkthng/following{/other_user}","gists_url":"https://api.github.com/users/drkthng/gists{/gist_id}","starred_url":"https://api.github.com/users/drkthng/starred{/owner}{/repo}","subscriptions_url":"https://api.github.com/users/drkthng/subscriptions","organizations_url":"https://api.github.com/users/drkthng/orgs","repos_url":"https://api.github.com/users/drkthng/repos","events_url":"https://api.github.com/users/drkthng/events{/privacy}","received_events_url":"https://api.github.com/users/drkthng/received_events","type":"User","site_admin":false}},{"starred_at":"2020-06-22T09:32:11Z","user":{"login":"rgaida","id":1970218,"node_id":"MDQ6VXNlcjE5NzAyMTg=","avatar_url":"https://avatars.githubusercontent.com/u/1970218?v=4","gravatar_id":"","url":"https://api.github.com/users/rgaida","html_url":"https://github.com/rgaida","followers_url":"https://api.github.com/users/rgaida/followers","following_url":"https://api.github.com/users/rgaida/following{/other_user}","gists_url":"https://api.github.com/users/rgaida/gists{/gist_id}","starred_url":"https://api.github.com/users/rgaida/starred{/owner}{/repo}","subscriptions_url":"https://api.github.com/users/rgaida/subscriptions","organizations_url":"https://api.github.com/users/rgaida/orgs","repos_url":"https://api.github.com/users/rgaida/repos","events_url":"https://api.github.com/users/rgaida/events{/privacy}","received_events_url":"https://api.github.com/users/rgaida/received_events","type":"User","site_admin":false}},{"starred_at":"2020-06-22T10:57:36Z","user":{"login":"cosmincatalin","id":525590,"node_id":"MDQ6VXNlcjUyNTU5MA==","avatar_url":"https://avatars.githubusercontent.com/u/525590?v=4","gravatar_id":"","url":"https://api.github.com/users/cosmincatalin","html_url":"https://github.com/cosmincatalin","followers_url":"https://api.github.com/users/cosmincatalin/followers","following_url":"https://api.github.com/users/cosmincatalin/following{/other_user}","gists_url":"https://api.github.com/users/cosmincatalin/gists{/gist_id}","starred_url":"https://api.github.com/users/cosmincatalin/starred{/owner}{/repo}","subscriptions_url":"https://api.github.com/users/cosmincatalin/subscriptions","organizations_url":"https://api.github.com/users/cosmincatalin/orgs","repos_url":"https://api.github.com/users/cosmincatalin/repos","events_url":"https://api.github.com/users/cosmincatalin/events{/privacy}","received_events_url":"https://api.github.com/users/cosmincatalin/received_events","type":"User","site_admin":false}},{"starred_at":"2020-06-24T02:21:37Z","user":{"login":"haoyunZhou","id":13463742,"node_id":"MDQ6VXNlcjEzNDYzNzQy","avatar_url":"https://avatars.githubusercontent.com/u/13463742?v=4","gravatar_id":"","url":"https://api.github.com/users/haoyunZhou","html_url":"https://github.com/haoyunZhou","followers_url":"https://api.github.com/users/haoyunZhou/followers","following_url":"https://api.github.com/users/haoyunZhou/following{/other_user}","gists_url":"https://api.github.com/users/haoyunZhou/gists{/gist_id}","starred_url":"https://api.github.com/users/haoyunZhou/starred{/owner}{/repo}","subscriptions_url":"https://api.github.com/users/haoyunZhou/subscriptions","organizations_url":"https://api.github.com/users/haoyunZhou/orgs","repos_url":"https://api.github.com/users/haoyunZhou/repos","events_url":"https://api.github.com/users/haoyunZhou/events{/privacy}","received_events_url":"https://api.github.com/users/haoyunZhou/received_events","type":"User","site_admin":false}}]